ttcore/admin.html
ttcore/admin.py
ttcore/bottle.py
ttcore/cli.py
ttcore/docs.html
ttcore/ip.py
ttcore/mailers.py
ttcore/messages.py
ttcore/peewee.py
ttcore/utils.py
ttcore-0.1.25.dist-info/LICENSE.txt
ttcore-0.1.25.dist-info/METADATA
ttcore-0.1.25.dist-info/WHEEL
ttcore-0.1.25.dist-info/entry_points.txt
ttcore-0.1.25.dist-info/top_level.txt
ttcore-0.1.25.dist-info/zip-safe
ttcore-0.1.25.dist-info/RECORD
