Metadata-Version: 2.1
Name: ttcore
Version: 0.1.25
Summary: Atomic Batteries Included. Used by https://tigerteamx.com to maximize producitivty.
Home-page: https://github.com/tigerteamx/ttcore
Author: Martin F
Author-email: pypi.org@tigerteamx.com
Keywords: productivity,bottlepy,peewee
Classifier: Programming Language :: Python :: 3
Classifier: License :: OSI Approved :: MIT License
Classifier: Operating System :: OS Independent
Requires-Python: >=3.8
License-File: LICENSE.txt
Requires-Dist: requests ==2.28.0
Requires-Dist: docopt ==0.6.2
Requires-Dist: cryptography ==41.0.2
